setup.py
tapioca_twitter/__init__.py
tapioca_twitter/resource_mapping.py
tapioca_twitter/tapioca_twitter.py
tapioca_twitter.egg-info/PKG-INFO
tapioca_twitter.egg-info/SOURCES.txt
tapioca_twitter.egg-info/dependency_links.txt
tapioca_twitter.egg-info/not-zip-safe
tapioca_twitter.egg-info/requires.txt
tapioca_twitter.egg-info/top_level.txt