Metadata-Version: 1.1
Name: tapioca-twitter
Version: 0.8.3
Summary: Twitter API wrapper using tapioca
Home-page: https://github.com/vintasoftware/tapioca-twitter
Author: Filipe Ximenes
Author-email: filipeximenes@gmail.com
License: BSD
Keywords: tapioca_twitter
Platform: UNKNOWN
Classifier: Development Status :: 5 - Production/Stable
Classifier: Intended Audience :: Developers
Classifier: License :: OSI Approved :: MIT License
Classifier: Natural Language :: English
Classifier: Programming Language :: Python :: 2
Classifier: Programming Language :: Python :: 3
